LICENSE
MANIFEST.in
README.md
setup.py
fastcv/__init__.py
fastcv/cast.py
fastcv/concat.py
fastcv/converter.py
fastcv/dataloader.py
fastcv/draw_text.py
fastcv/environment.py
fastcv/face.py
fastcv/filter.py
fastcv/onnx_model.py
fastcv/resize.py
fastcv/tensor.py
fastcv/timer.py
fastcv/utils.py
fastcv.egg-info/PKG-INFO
fastcv.egg-info/SOURCES.txt
fastcv.egg-info/dependency_links.txt
fastcv.egg-info/not-zip-safe
fastcv.egg-info/requires.txt
fastcv.egg-info/top_level.txt
fastcv/draw/__init__.py
fastcv/io/__init__.py
fastcv/io/ffmpeg_utils.py
fastcv/io/video_utils.py
fastcv/io/view.py
test/test_cast.py
test/test_draw.py
test/test_example.py
test/test_facealign.py
test/test_ffmpeg.py
test/test_iw.py